LICENSE
MANIFEST.in
README.rst
setup.py
django_smartmenus.egg-info/PKG-INFO
django_smartmenus.egg-info/SOURCES.txt
django_smartmenus.egg-info/dependency_links.txt
django_smartmenus.egg-info/not-zip-safe
django_smartmenus.egg-info/top_level.txt
smartmenus/__init__.py
smartmenus/admin.py
smartmenus/models.py
smartmenus/tests.py
smartmenus/views.py
smartmenus/static/smartmenus/initialize.js
smartmenus/static/smartmenus/jquery.smartmenus.js
smartmenus/static/smartmenus/jquery.smartmenus.min.js
smartmenus/static/smartmenus/addons/bootstrap/jquery.smartmenus.bootstrap.css
smartmenus/static/smartmenus/addons/bootstrap/jquery.smartmenus.bootstrap.js
smartmenus/static/smartmenus/addons/bootstrap/jquery.smartmenus.bootstrap.min.js
smartmenus/static/smartmenus/addons/keyboard/jquery.smartmenus.keyboard.js
smartmenus/static/smartmenus/addons/keyboard/jquery.smartmenus.keyboard.min.js
smartmenus/static/smartmenus/css/sm-core-css.css
smartmenus/static/smartmenus/css/sm-blue/sm-blue.css
smartmenus/static/smartmenus/css/sm-blue/css-gradients-fallback/current-item-bg.png
smartmenus/static/smartmenus/css/sm-blue/css-gradients-fallback/main-item-hover-bg.png
smartmenus/static/smartmenus/css/sm-blue/css-gradients-fallback/main-menu-bg.png
smartmenus/static/smartmenus/css/sm-blue/css-gradients-fallback/sub-item-hover-bg.png
smartmenus/static/smartmenus/css/sm-blue/css-gradients-fallback/vertical-main-item-bg.png
smartmenus/static/smartmenus/css/sm-clean/sm-clean.css
smartmenus/static/smartmenus/css/sm-mint/sm-mint.css
smartmenus/static/smartmenus/css/sm-simple/sm-simple.css
smartmenus/templates/menu/menu.html
smartmenus/templates/smartmenus/bootstrap_cms.html
smartmenus/templates/smartmenus/core_css.html
smartmenus/templates/smartmenus/core_js.html
smartmenus/templates/smartmenus/css.html
smartmenus/templates/smartmenus/init_js.html
smartmenus/templates/smartmenus/js.html
smartmenus/templates/smartmenus/smartmenus_css.html
smartmenus/templates/smartmenus/smartmenus_js.html
smartmenus/templates/smartmenus/theme_css.html
smartmenus/templatetags/__init__.py
smartmenus/templatetags/smartmenus_tags.py